singlefile_mcp_server.py
singlefile_mcp-0.1.1.dist-info/licenses/LICENSE
singlefile_mcp-0.1.1.dist-info/METADATA
singlefile_mcp-0.1.1.dist-info/WHEEL
singlefile_mcp-0.1.1.dist-info/entry_points.txt
singlefile_mcp-0.1.1.dist-info/top_level.txt
singlefile_mcp-0.1.1.dist-info/RECORD
