Metadata-Version: 2.4
Name: singlefile-mcp
Version: 0.1.1
Summary: MCP server for intelligent web content extraction using single-file and trafilatura
Author-email: Kevin Bortis <kevin@bortis.ch>
License-Expression: MIT
Project-URL: Homepage, https://github.com/kwinsch/singlefile-mcp
Project-URL: Issues, https://github.com/kwinsch/singlefile-mcp/issues
Project-URL: Repository, https://github.com/kwinsch/singlefile-mcp
Keywords: mcp,model-context-protocol,web-scraping,content-extraction,single-file,trafilatura,ai,llm
Classifier: Development Status :: 4 - Beta
Classifier: Intended Audience :: Developers
Classifier: Programming Language :: Python :: 3
Classifier: Programming Language :: Python :: 3.8
Classifier: Programming Language :: Python :: 3.9
Classifier: Programming Language :: Python :: 3.10
Classifier: Programming Language :: Python :: 3.11
Classifier: Programming Language :: Python :: 3.12
Requires-Python: >=3.8
License-File: LICENSE
Requires-Dist: mcp==1.0.0
Requires-Dist: trafilatura==2.0.0
Dynamic: license-file
